funnydeco/__init__.py
funnydeco/core.py
funnydeco-0.1.7.dist-info/LICENSE
funnydeco-0.1.7.dist-info/METADATA
funnydeco-0.1.7.dist-info/WHEEL
funnydeco-0.1.7.dist-info/top_level.txt
funnydeco-0.1.7.dist-info/RECORD
