Metadata-Version: 2.1
Name: funnydeco
Version: 0.1.7
Summary: Collection of useful decorators for various python projects
Home-page: https://gitflic.ru/project/vlakir/funnydeco
Author: Vladimir Kirievskiy
Author-email: vladimir@kirievskiy.ru
License: UNKNOWN
Platform: UNKNOWN
Classifier: Programming Language :: Python :: 3.9
Classifier: License :: OSI Approved :: GNU General Public License v3 (GPLv3)
License-File: LICENSE
